flirimageextractor/__init__.py
flirimageextractor/__main__.py
flirimageextractor/dialogs.py
flirimageextractor/flir_image_extractor.py
flirimageextractor/flyr_unpack.py
flirimageextractor/processing.py
flirimageextractor/thermal.py
flirimageextractor/thermal_base.py
flirimageextractor/utils.py
flirimageextractor-1.5.9.dist-info/LICENSE
flirimageextractor-1.5.9.dist-info/METADATA
flirimageextractor-1.5.9.dist-info/WHEEL
flirimageextractor-1.5.9.dist-info/entry_points.txt
flirimageextractor-1.5.9.dist-info/RECORD
