Metadata-Version: 2.3
Name: flirimageextractor
Version: 1.5.9
Summary: A small tool/lib to read temperatures and original photos from FLIR® thermal camera images.
License: MIT
Keywords: extract-images,flir,thermal,flirtools
Author: National Drones
Author-email: development@nationaldrones.com
Maintainer: olawale williams
Maintainer-email: olawalewilliams9438@gmail.com
Requires-Python: >=3.10,<4.0
Classifier: Intended Audience :: Science/Research
Classifier: License :: OSI Approved :: MIT License
Classifier: Operating System :: OS Independent
Classifier: Programming Language :: Python :: 3
Classifier: Programming Language :: Python :: 3.10
Classifier: Programming Language :: Python :: 3.11
Classifier: Programming Language :: Python :: 3.12
Classifier: Programming Language :: Python :: 3.13
Classifier: Topic :: Multimedia :: Graphics :: Capture :: Digital Camera
Requires-Dist: keyring (>=25.2.1,<26.0.0)
Requires-Dist: loguru (>=0.7.2,<0.8.0)
Requires-Dist: logzero (>=1.7.0,<2.0.0)
Requires-Dist: matplotlib (>=3.9.0,<4.0.0)
Requires-Dist: numpy (>=2.0.0,<3.0.0)
Requires-Dist: opencv-python (>=4.10.0.84,<5.0.0.0)
Requires-Dist: pillow (>=10.3.0,<11.0.0)
Requires-Dist: requests (>=2.32.3,<3.0.0)
Requires-Dist: sphinx (>=7.3.7,<8.0.0)
Requires-Dist: tqdm (>=4.66.4,<5.0.0)
Project-URL: Documentation, https://github.com/nationaldronesau/FlirImageExtractor
Project-URL: Homepage, https://github.com/nationaldronesau/FlirImageExtractor
Project-URL: Repository, https://github.com/nationaldronesau/FlirImageExtractor
